aissemble_open_inference_protocol_grpc/__init__.py
aissemble_open_inference_protocol_grpc/aissemble_oip_grpc.py
aissemble_open_inference_protocol_grpc/auth/auth_interceptor.py
aissemble_open_inference_protocol_grpc/grpc_inference_service_pb2.py
aissemble_open_inference_protocol_grpc/grpc_inference_service_pb2.pyi
aissemble_open_inference_protocol_grpc/grpc_inference_service_pb2_grpc.py
aissemble_open_inference_protocol_grpc/inference_servicer.py
aissemble_open_inference_protocol_grpc/mappers/model_inference_request_mapper.py
aissemble_open_inference_protocol_grpc/mappers/model_inference_response_mapper.py
aissemble_open_inference_protocol_grpc/mappers/model_metadata_response_mapper.py
aissemble_open_inference_protocol_grpc/mappers/utils.py
aissemble_open_inference_protocol_grpc-1.1.0.dist-info/METADATA
aissemble_open_inference_protocol_grpc-1.1.0.dist-info/WHEEL
aissemble_open_inference_protocol_grpc-1.1.0.dist-info/licenses/LICENSE.txt
aissemble_open_inference_protocol_grpc-1.1.0.dist-info/RECORD
