Metadata-Version: 2.4
Name: aissemble-open-inference-protocol-grpc
Version: 1.1.0
Summary: A gRPC implementation of the Open Inference Protocol
License-Expression: Apache-2.0
License-File: LICENSE.txt
Author: aiSSEMBLE Solutions Community
Author-email: aissemble@bah.com
Requires-Python: >=3.10,<3.13
Classifier: Programming Language :: Python :: 3
Classifier: Programming Language :: Python :: 3.10
Classifier: Programming Language :: Python :: 3.11
Classifier: Programming Language :: Python :: 3.12
Classifier: License :: Other/Proprietary License
Classifier: Operating System :: OS Independent
Classifier: Intended Audience :: Developers
Requires-Dist: PyJWT (>=2.10.1,<3.0.0)
Requires-Dist: aissemble-open-inference-protocol-shared (==1.1.0)
Requires-Dist: cryptography (>=44.0.1)
Requires-Dist: grpcio (>=1.73.0,<2.0.0)
Requires-Dist: grpcio-tools (>=1.73.0,<2.0.0)
Requires-Dist: krausening (>=20,<21)
Project-URL: Homepage, https://github.com/boozallen/aissemble-open-inference-protocol
